setup.py
blackjack_am/Card.py
blackjack_am/Game.py
blackjack_am/Person.py
blackjack_am/__init__.py
blackjack_am.egg-info/PKG-INFO
blackjack_am.egg-info/SOURCES.txt
blackjack_am.egg-info/dependency_links.txt
blackjack_am.egg-info/not-zip-safe
blackjack_am.egg-info/top_level.txt