Metadata-Version: 1.0
Name: blackjack-am
Version: 0.1
Summary: Blackjack (21) single player game
Home-page: UNKNOWN
Author: Alcia Moncrieffe
Author-email: alcia.moncrieffe@gmail.com
License: UNKNOWN
Platform: UNKNOWN
